{
  "$schema": "https://raw.githubusercontent.com/spdx/spdx-spec/v2.2.1/schemas/spdx-schema.json",
  "spdxVersion": "SPDX-2.2",
  "dataLicense": "CC0-1.0",
  "SPDXID": "SPDXRef-DOCUMENT",
  "documentNamespace": "https://spdx.org/spdxdocs/gettext-x86-windows-0.21.1#3-dcb9d787-a0ac-47d8-9559-81cc83907985",
  "name": "gettext:x86-windows@0.21.1#3 e3d07557a0c42788f21fb75893ee3a592c62f06e8a50a3e0918f0170434fe51c",
  "creationInfo": {
    "creators": [
      "Tool: vcpkg-8a83681f921b10d86ae626fd833c253f4f8c355b"
    ],
    "created": "2024-03-02T22:25:11Z"
  },
  "relationships": [
    {
      "spdxElementId": "SPDXRef-port",
      "relationshipType": "GENERATES",
      "relatedSpdxElement": "SPDXRef-binary"
    },
    {
      "spdxElementId": "SPDXRef-port",
      "relationshipType": "CONTAINS",
      "relatedSpdxElement": "SPDXRef-file-0"
    },
    {
      "spdxElementId": "SPDXRef-port",
      "relationshipType": "CONTAINS",
      "relatedSpdxElement": "SPDXRef-file-1"
    },
    {
      "spdxElementId": "SPDXRef-port",
      "relationshipType": "CONTAINS",
      "relatedSpdxElement": "SPDXRef-file-2"
    },
    {
      "spdxElementId": "SPDXRef-port",
      "relationshipType": "CONTAINS",
      "relatedSpdxElement": "SPDXRef-file-3"
    },
    {
      "spdxElementId": "SPDXRef-port",
      "relationshipType": "CONTAINS",
      "relatedSpdxElement": "SPDXRef-file-4"
    },
    {
      "spdxElementId": "SPDXRef-port",
      "relationshipType": "CONTAINS",
      "relatedSpdxElement": "SPDXRef-file-5"
    },
    {
      "spdxElementId": "SPDXRef-port",
      "relationshipType": "CONTAINS",
      "relatedSpdxElement": "SPDXRef-file-6"
    },
    {
      "spdxElementId": "SPDXRef-port",
      "relationshipType": "CONTAINS",
      "relatedSpdxElement": "SPDXRef-file-7"
    },
    {
      "spdxElementId": "SPDXRef-port",
      "relationshipType": "CONTAINS",
      "relatedSpdxElement": "SPDXRef-file-8"
    },
    {
      "spdxElementId": "SPDXRef-port",
      "relationshipType": "CONTAINS",
      "relatedSpdxElement": "SPDXRef-file-9"
    },
    {
      "spdxElementId": "SPDXRef-port",
      "relationshipType": "CONTAINS",
      "relatedSpdxElement": "SPDXRef-file-10"
    },
    {
      "spdxElementId": "SPDXRef-port",
      "relationshipType": "CONTAINS",
      "relatedSpdxElement": "SPDXRef-file-11"
    },
    {
      "spdxElementId": "SPDXRef-port",
      "relationshipType": "CONTAINS",
      "relatedSpdxElement": "SPDXRef-file-12"
    },
    {
      "spdxElementId": "SPDXRef-binary",
      "relationshipType": "GENERATED_FROM",
      "relatedSpdxElement": "SPDXRef-port"
    },
    {
      "spdxElementId": "SPDXRef-file-0",
      "relationshipType": "CONTAINED_BY",
      "relatedSpdxElement": "SPDXRef-port"
    },
    {
      "spdxElementId": "SPDXRef-file-1",
      "relationshipType": "CONTAINED_BY",
      "relatedSpdxElement": "SPDXRef-port"
    },
    {
      "spdxElementId": "SPDXRef-file-2",
      "relationshipType": "CONTAINED_BY",
      "relatedSpdxElement": "SPDXRef-port"
    },
    {
      "spdxElementId": "SPDXRef-file-3",
      "relationshipType": "CONTAINED_BY",
      "relatedSpdxElement": "SPDXRef-port"
    },
    {
      "spdxElementId": "SPDXRef-file-4",
      "relationshipType": "CONTAINED_BY",
      "relatedSpdxElement": "SPDXRef-port"
    },
    {
      "spdxElementId": "SPDXRef-file-5",
      "relationshipType": "CONTAINED_BY",
      "relatedSpdxElement": "SPDXRef-port"
    },
    {
      "spdxElementId": "SPDXRef-file-6",
      "relationshipType": "CONTAINED_BY",
      "relatedSpdxElement": "SPDXRef-port"
    },
    {
      "spdxElementId": "SPDXRef-file-7",
      "relationshipType": "CONTAINED_BY",
      "relatedSpdxElement": "SPDXRef-port"
    },
    {
      "spdxElementId": "SPDXRef-file-8",
      "relationshipType": "CONTAINED_BY",
      "relatedSpdxElement": "SPDXRef-port"
    },
    {
      "spdxElementId": "SPDXRef-file-9",
      "relationshipType": "CONTAINED_BY",
      "relatedSpdxElement": "SPDXRef-port"
    },
    {
      "spdxElementId": "SPDXRef-file-10",
      "relationshipType": "CONTAINED_BY",
      "relatedSpdxElement": "SPDXRef-port"
    },
    {
      "spdxElementId": "SPDXRef-file-11",
      "relationshipType": "CONTAINED_BY",
      "relatedSpdxElement": "SPDXRef-port"
    },
    {
      "spdxElementId": "SPDXRef-file-12",
      "relationshipType": "CONTAINED_BY",
      "relatedSpdxElement": "SPDXRef-port"
    }
  ],
  "packages": [
    {
      "name": "gettext",
      "SPDXID": "SPDXRef-port",
      "versionInfo": "0.21.1#3",
      "downloadLocation": "git+https://github.com/microsoft/vcpkg@20e8e3535959bba6066d8887bb1c95e622d86f5a",
      "homepage": "https://www.gnu.org/software/gettext/",
      "licenseConcluded": "GPL-3.0-only",
      "licenseDeclared": "NOASSERTION",
      "copyrightText": "NOASSERTION",
      "description": "A GNU framework to help produce multi-lingual messages.",
      "comment": "This is the port (recipe) consumed by vcpkg."
    },
    {
      "name": "gettext:x86-windows",
      "SPDXID": "SPDXRef-binary",
      "versionInfo": "e3d07557a0c42788f21fb75893ee3a592c62f06e8a50a3e0918f0170434fe51c",
      "downloadLocation": "NONE",
      "licenseConcluded": "GPL-3.0-only",
      "licenseDeclared": "NOASSERTION",
      "copyrightText": "NOASSERTION",
      "comment": "This is a binary package built by vcpkg."
    },
    {
      "SPDXID": "SPDXRef-resource-1",
      "name": "gettext-${VERSION}.tar.gz",
      "packageFileName": "gettext-${VERSION}.tar.gz",
      "downloadLocation": "https://ftp.gnu.org/pub/gnu/gettext/gettext-${VERSION}.tar.gz",
      "licenseConcluded": "NOASSERTION",
      "licenseDeclared": "NOASSERTION",
      "copyrightText": "NOASSERTION",
      "checksums": [
        {
          "algorithm": "SHA512",
          "checksumValue": "ccd43a43fab3c90ed99b3e27628c9aeb7186398153b137a4997f8c7ddfd9729b0ba9d15348567e5206af50ac027673d2b8a3415bb3fc65f87ad778f85dc03a05"
        }
      ]
    }
  ],
  "files": [
    {
      "fileName": "./C:/Users/shadowlerone/AppData/Local/vcpkg/registries/git-trees/20e8e3535959bba6066d8887bb1c95e622d86f5a/0003-Fix-win-unicode-paths.patch",
      "SPDXID": "SPDXRef-file-0",
      "checksums": [
        {
          "algorithm": "SHA256",
          "checksumValue": "2ef9ec9d0fdf4fad272c17942350c380509cf06ec84e7ea646177439b6cea4fe"
        }
      ],
      "licenseConcluded": "NOASSERTION",
      "copyrightText": "NOASSERTION"
    },
    {
      "fileName": "./C:/Users/shadowlerone/AppData/Local/vcpkg/registries/git-trees/20e8e3535959bba6066d8887bb1c95e622d86f5a/android.patch",
      "SPDXID": "SPDXRef-file-1",
      "checksums": [
        {
          "algorithm": "SHA256",
          "checksumValue": "2378da97ddc12bf0653e0e0fd1ee72b1c89ec90e02f9b7134d76d655b49608f5"
        }
      ],
      "licenseConcluded": "NOASSERTION",
      "copyrightText": "NOASSERTION"
    },
    {
      "fileName": "./C:/Users/shadowlerone/AppData/Local/vcpkg/registries/git-trees/20e8e3535959bba6066d8887bb1c95e622d86f5a/bashify.cmake",
      "SPDXID": "SPDXRef-file-2",
      "checksums": [
        {
          "algorithm": "SHA256",
          "checksumValue": "232f0e8bbaa56e78b4363c3996a21d225b71f278d870959036ee2addb0bb3875"
        }
      ],
      "licenseConcluded": "NOASSERTION",
      "copyrightText": "NOASSERTION"
    },
    {
      "fileName": "./C:/Users/shadowlerone/AppData/Local/vcpkg/registries/git-trees/20e8e3535959bba6066d8887bb1c95e622d86f5a/install-autopoint.cmake",
      "SPDXID": "SPDXRef-file-3",
      "checksums": [
        {
          "algorithm": "SHA256",
          "checksumValue": "f139103408f5b43ad8d4497839da22a41a3a7cc58b3a0c7232f90d57e4614ab1"
        }
      ],
      "licenseConcluded": "NOASSERTION",
      "copyrightText": "NOASSERTION"
    },
    {
      "fileName": "./C:/Users/shadowlerone/AppData/Local/vcpkg/registries/git-trees/20e8e3535959bba6066d8887bb1c95e622d86f5a/macosx-libs.patch",
      "SPDXID": "SPDXRef-file-4",
      "checksums": [
        {
          "algorithm": "SHA256",
          "checksumValue": "df405e707d80e26e4d35285d983d6ab26967288f3b3253b6e4351b2cf856cda7"
        }
      ],
      "licenseConcluded": "NOASSERTION",
      "copyrightText": "NOASSERTION"
    },
    {
      "fileName": "./C:/Users/shadowlerone/AppData/Local/vcpkg/registries/git-trees/20e8e3535959bba6066d8887bb1c95e622d86f5a/parallel-gettext-tools.patch",
      "SPDXID": "SPDXRef-file-5",
      "checksums": [
        {
          "algorithm": "SHA256",
          "checksumValue": "b2ac56bc5a10c69611b808f8d82fda132931712c2357590403fe8f02b5d8472e"
        }
      ],
      "licenseConcluded": "NOASSERTION",
      "copyrightText": "NOASSERTION"
    },
    {
      "fileName": "./C:/Users/shadowlerone/AppData/Local/vcpkg/registries/git-trees/20e8e3535959bba6066d8887bb1c95e622d86f5a/portfile.cmake",
      "SPDXID": "SPDXRef-file-6",
      "checksums": [
        {
          "algorithm": "SHA256",
          "checksumValue": "70b5fb1b6ddd7bf4821e49eacd8a02a136a425d9b83994831fe2fbc92447ce77"
        }
      ],
      "licenseConcluded": "NOASSERTION",
      "copyrightText": "NOASSERTION"
    },
    {
      "fileName": "./C:/Users/shadowlerone/AppData/Local/vcpkg/registries/git-trees/20e8e3535959bba6066d8887bb1c95e622d86f5a/rel_path.patch",
      "SPDXID": "SPDXRef-file-7",
      "checksums": [
        {
          "algorithm": "SHA256",
          "checksumValue": "79dd583f66249bc5de93fda04348d46c84edfafac5c830457f8609ed726793ec"
        }
      ],
      "licenseConcluded": "NOASSERTION",
      "copyrightText": "NOASSERTION"
    },
    {
      "fileName": "./C:/Users/shadowlerone/AppData/Local/vcpkg/registries/git-trees/20e8e3535959bba6066d8887bb1c95e622d86f5a/subdirs.patch",
      "SPDXID": "SPDXRef-file-8",
      "checksums": [
        {
          "algorithm": "SHA256",
          "checksumValue": "fb38929c365472bbe1a6b07ac410468b166888ea88d0f3cefab8de6fc78b1b7f"
        }
      ],
      "licenseConcluded": "NOASSERTION",
      "copyrightText": "NOASSERTION"
    },
    {
      "fileName": "./C:/Users/shadowlerone/AppData/Local/vcpkg/registries/git-trees/20e8e3535959bba6066d8887bb1c95e622d86f5a/uwp.patch",
      "SPDXID": "SPDXRef-file-9",
      "checksums": [
        {
          "algorithm": "SHA256",
          "checksumValue": "54748fc750ab4f69eabc334ec45ffad8003630d5d8789d1fc9201aabf701c4c4"
        }
      ],
      "licenseConcluded": "NOASSERTION",
      "copyrightText": "NOASSERTION"
    },
    {
      "fileName": "./C:/Users/shadowlerone/AppData/Local/vcpkg/registries/git-trees/20e8e3535959bba6066d8887bb1c95e622d86f5a/vcpkg-port-config.cmake",
      "SPDXID": "SPDXRef-file-10",
      "checksums": [
        {
          "algorithm": "SHA256",
          "checksumValue": "4ca96b14a5e1b7a76c4aaf8560c04053ee51df2a40149be6c60b7e228b529863"
        }
      ],
      "licenseConcluded": "NOASSERTION",
      "copyrightText": "NOASSERTION"
    },
    {
      "fileName": "./C:/Users/shadowlerone/AppData/Local/vcpkg/registries/git-trees/20e8e3535959bba6066d8887bb1c95e622d86f5a/vcpkg.json",
      "SPDXID": "SPDXRef-file-11",
      "checksums": [
        {
          "algorithm": "SHA256",
          "checksumValue": "031019f4eeeee32262f33ea49b5fa71236455aac4440fa8dbefe6aa4152aac5e"
        }
      ],
      "licenseConcluded": "NOASSERTION",
      "copyrightText": "NOASSERTION"
    },
    {
      "fileName": "./C:/Users/shadowlerone/AppData/Local/vcpkg/registries/git-trees/20e8e3535959bba6066d8887bb1c95e622d86f5a/win-gethostname.patch",
      "SPDXID": "SPDXRef-file-12",
      "checksums": [
        {
          "algorithm": "SHA256",
          "checksumValue": "06a28abc741bae5c23c3c4a0a5647eda20a8853eedb93f58838c02508eec33b8"
        }
      ],
      "licenseConcluded": "NOASSERTION",
      "copyrightText": "NOASSERTION"
    }
  ]
}
